smoothtransitions/__init__.py
smoothtransitions/logger_config.yaml
smoothtransitions/smoothtransitions.py
smoothtransitions/subcommands/__init__.py
smoothtransitions/subcommands/gaussian_io.py
smoothtransitions/subcommands/reporting.py
smoothtransitions/subcommands/runner.py
smoothtransitions/subcommands/utils/__init__.py
smoothtransitions/subcommands/utils/gaussian_ts.py
smoothtransitions/subcommands/utils/utils.py
smoothtransitions/subcommands/workflow.py
smoothtransitions/subcommands/workflow_log.py
smoothtransitions-0.4.1.dist-info/entry_points.txt
smoothtransitions-0.4.1.dist-info/LICENSE
smoothtransitions-0.4.1.dist-info/WHEEL
smoothtransitions-0.4.1.dist-info/METADATA
smoothtransitions-0.4.1.dist-info/RECORD
