Metadata-Version: 2.1
Name: smoothtransitions
Version: 0.4.1
Summary: 
License: MIT
Author: Florian Roessler
Author-email: smoothtransitions.github@gmail.com
Requires-Python: >=3.7.1,<4.0.0
Classifier: License :: OSI Approved :: MIT License
Classifier: Programming Language :: Python :: 3
Classifier: Programming Language :: Python :: 3.8
Classifier: Programming Language :: Python :: 3.9
Requires-Dist: PyYAML (>=5.4.1,<6.0.0)
Requires-Dist: cclib (>=1.7,<2.0)
Requires-Dist: click (>=7.1.2,<8.0.0)
Requires-Dist: matplotlib (>=3.3.4,<4.0.0)
Requires-Dist: numpy (>=1.20.1,<2.0.0)
Requires-Dist: pandas (>=1.2.3,<2.0.0)
Requires-Dist: tabulate (>=0.8.9,<0.9.0)
Requires-Dist: typer (>=0.3.2,<0.4.0)
